oswrite/__init__.py
oswrite/__main__.py
oswrite/cli.py
oswrite-0.0.2.dist-info/METADATA
oswrite-0.0.2.dist-info/WHEEL
oswrite-0.0.2.dist-info/entry_points.txt
oswrite-0.0.2.dist-info/top_level.txt
oswrite-0.0.2.dist-info/RECORD
