Metadata-Version: 2.1
Name: oswrite
Version: 0.0.2
Summary: CLI tool for processing audio files
Author: Prabin Nepal
License: Apache-2.0
Project-URL: Homepage, https://github.com/nepalprabin/oswrite
Project-URL: Changelog, https://github.com/nepalprabin/oswrite/releases
Project-URL: Issues, https://github.com/nepalprabin/oswrite/issues
Project-URL: CI, https://github.com/nepalprabin/osread/actions
Classifier: License :: OSI Approved :: Apache Software License
Requires-Python: >=3.8
Requires-Dist: click
Requires-Dist: python-docx
Requires-Dist: openai >=1.0
Requires-Dist: simpleaudio ; sys_platform == "darwin"
Provides-Extra: test
Requires-Dist: pytest ; extra == 'test'
Requires-Dist: cogapp ; extra == 'test'
